elsw/__init__.py
elsw-1.0.1.dist-info/entry_points.txt
elsw-1.0.1.dist-info/LICENSE.txt
elsw-1.0.1.dist-info/WHEEL
elsw-1.0.1.dist-info/METADATA
elsw-1.0.1.dist-info/RECORD
