Metadata-Version: 2.3
Name: elsw
Version: 1.0.1
Summary: A nice way to view Portage world file.
Author-email: Maciej Barć <xgqt@xgqt.org>
Requires-Python: >=3.8
Classifier: Environment :: Console
Classifier: Intended Audience :: System Administrators
Classifier: License :: OSI Approved :: GNU General Public License v2 (GPLv2)
Classifier: Operating System :: POSIX
Classifier: Programming Language :: Python :: 3 :: Only
Requires-Dist: colorama
Requires-Dist: portage
Project-URL: Home, https://gitlab.com/xgqt/python-elsw/
